datagen.py
base/__init__.py
base/logger.py
build_upgrade_package-0.1.9.dist-info/METADATA
build_upgrade_package-0.1.9.dist-info/WHEEL
build_upgrade_package-0.1.9.dist-info/entry_points.txt
build_upgrade_package-0.1.9.dist-info/top_level.txt
build_upgrade_package-0.1.9.dist-info/RECORD
